dff.v
// ===========================================================================
//
// Description:
//  Verilog module sirv_gnrl DFF with Load-enable and Reset
//  Default reset value is 1
//
// ===========================================================================
module dfflrs # (
  parameter DW = 32
) (

  input               lden, 
  input      [DW-1:0] dnxt,
  output     [DW-1:0] qout,

  input               clk,
  input               rst_n
);

reg [DW-1:0] qout_r;

always @(posedge clk or negedge rst_n)
begin : DFFLRS_PROC
  if (rst_n == 1'b0)
    qout_r <= {DW{1'b1}};
  else if (lden == 1'b1)
    qout_r <= #1 dnxt;
end

assign qout = qout_r;


endmodule
// ===========================================================================
//
// Description:
//  Verilog module sirv_gnrl DFF with Load-enable and Reset
//  Default reset value is 0
//
// ===========================================================================

module dfflr # (
  parameter DW = 32
) (

  input               lden, 
  input      [DW-1:0] dnxt,
  output     [DW-1:0] qout,

  input               clk,
  input               rst_n
);

reg [DW-1:0] qout_r;

always @(posedge clk or negedge rst_n)
begin : DFFLR_PROC
  if (rst_n == 1'b0)
    qout_r <= {DW{1'b0}};
  else if (lden == 1'b1)
    qout_r <= #1 dnxt;
end

assign qout = qout_r;


endmodule
// ===========================================================================
//
// Description:
//  Verilog module sirv_gnrl DFF with Load-enable, no reset 
//
// ===========================================================================

module dffl # (
  parameter DW = 32
) (

  input               lden, 
  input      [DW-1:0] dnxt,
  output     [DW-1:0] qout,

  input               clk 
);

reg [DW-1:0] qout_r;

always @(posedge clk)
begin : DFFL_PROC
  if (lden == 1'b1)
    qout_r <= /*#1*/ dnxt;
end

assign qout = qout_r;


endmodule
// ===========================================================================
//
// Description:
//  Verilog module sirv_gnrl DFF with Reset, no load-enable
//  Default reset value is 1
//
// ===========================================================================

module dffrs # (
  parameter DW = 32
) (

  input      [DW-1:0] dnxt,
  output     [DW-1:0] qout,

  input               clk,
  input               rst_n
);

reg [DW-1:0] qout_r;

always @(posedge clk or negedge rst_n)
begin : DFFRS_PROC
  if (rst_n == 1'b0)
    qout_r <= {DW{1'b1}};
  else                  
    qout_r <= /*#1*/ dnxt;
end

assign qout = qout_r;

endmodule
// ===========================================================================
//
// Description:
//  Verilog module sirv_gnrl DFF with Reset, no load-enable
//  Default reset value is 0
//
// ===========================================================================

module dffr # (
  parameter DW = 32
) (

  input      [DW-1:0] dnxt,
  output     [DW-1:0] qout,

  input               clk,
  input               rst_n
);

reg [DW-1:0] qout_r;

always @(posedge clk or negedge rst_n)
begin : DFFR_PROC
  if (rst_n == 1'b0)
    qout_r <= {DW{1'b0}};
  else                  
    qout_r <= /*#1*/ dnxt;
end

assign qout = qout_r;

endmodule
// ===========================================================================
//
// Description:
//  Verilog module for general latch 
//
// ===========================================================================

module sirv_gnrl_ltch # (
  parameter DW = 32
) (

  //input               test_mode,
  input               lden, 
  input      [DW-1:0] dnxt,
  output     [DW-1:0] qout
);

reg [DW-1:0] qout_r;

always @ (*) 
begin : LTCH_PROC
  if (lden == 1'b1)
    qout_r <= dnxt;
end

//assign qout = test_mode ? dnxt : qout_r;
assign qout = qout_r;


endmodule

count_pulse.v
module count_pulse # (
  parameter DW = 8
) (
  output qout,
  input [DW-1:0] in,
  input lden,
  input clk,
  input rst_n
);

  wire [DW-1:0] cur_cnt;
  wire [DW-1:0] nxt_cnt;
  wire [DW-1:0] minus_one;
  wire pos;

  assign pos = (cur_cnt > 0);
  assign minus_one =
          ({DW{ pos}} & cur_cnt - 1)
        | ({DW{~pos}} & 0);

  assign nxt_cnt =
          ({DW{~lden}} & minus_one)
        | ({DW{ lden}} & in);

  assign qout = (cur_cnt > 0) & clk;

  dffr #(DW) cnt_dffr (nxt_cnt, cur_cnt, clk, rst_n);

endmodule

pulse_tb.v
`timescale 1s/1ms
module pulse_tb;

reg [7:0] cnt;
reg clk;
reg rst_n;
reg lden;
wire pulse;

initial begin
    $dumpfile("pulse.vcd");
    $dumpvars(0, pulse_tb);
end

always #(0.5)
    clk = ~clk;

count_pulse #(8) c0 (pulse, cnt, lden, clk, rst_n);

initial begin
    cnt <= 9;
    clk <= 1'b0;
    lden <= 1'b0;
    rst_n <= 1'b0;
    #(1) rst_n <= 1'b1;
    #(1) lden <= 1'b1;
    #(1) lden <= 1'b0;
    //#(32) rst_n <= 1'b0;
    #(32) $finish;
end

endmodule

pulse.vcd
$date
	Thu Nov 17 16:30:14 2022
$end
$version
	Icarus Verilog
$end
$timescale
	1ms
$end
$scope module pulse_tb $end
$var wire 1 ! pulse $end
$var reg 1 " clk $end
$var reg 8 # cnt [7:0] $end
$var reg 1 $ lden $end
$var reg 1 % rst_n $end
$scope module c0 $end
$var wire 1 " clk $end
$var wire 8 & in [7:0] $end
$var wire 1 $ lden $end
$var wire 8 ' minus_one [7:0] $end
$var wire 8 ( nxt_cnt [7:0] $end
$var wire 1 ! qout $end
$var wire 1 % rst_n $end
$var wire 1 ) pos $end
$var wire 8 * cur_cnt [7:0] $end
$scope module cnt_dffr $end
$var wire 1 " clk $end
$var wire 8 + dnxt [7:0] $end
$var wire 1 % rst_n $end
$var wire 8 , qout [7:0] $end
$var reg 8 - qout_r [7:0] $end
$scope begin DFFR_PROC $end
$upscope $end
$upscope $end
$upscope $end
$upscope $end
$enddefinitions $end
#0
$dumpvars
b0 -
b0 ,
b0 +
b0 *
0)
b0 (
b0 '
b1001 &
0%
0$
b1001 #
0"
0!
$end
#500
1"
#1000
1%
0"
#1500
1"
#2000
b1001 (
b1001 +
1$
0"
#2500
b1000 '
1!
1)
b1001 *
b1001 ,
b1001 -
1"
#3000
b1000 (
b1000 +
0$
0!
0"
#3500
b111 (
b111 +
b111 '
b1000 *
b1000 ,
b1000 -
1!
1"
#4000
0!
0"
#4500
b110 (
b110 +
b110 '
b111 *
b111 ,
b111 -
1!
1"
#5000
0!
0"
#5500
b101 (
b101 +
b101 '
b110 *
b110 ,
b110 -
1!
1"
#6000
0!
0"
#6500
b100 (
b100 +
b100 '
b101 *
b101 ,
b101 -
1!
1"
#7000
0!
0"
#7500
b11 (
b11 +
b11 '
b100 *
b100 ,
b100 -
1!
1"
#8000
0!
0"
#8500
b10 (
b10 +
b10 '
b11 *
b11 ,
b11 -
1!
1"
#9000
0!
0"
#9500
b1 (
b1 +
b1 '
b10 *
b10 ,
b10 -
1!
1"
#10000
0!
0"
#10500
b0 (
b0 +
b0 '
b1 *
b1 ,
b1 -
1!
1"
#11000
0!
0"
#11500
0)
b0 *
b0 ,
b0 -
0!
1"
