dff.v
// ===========================================================================
//
// Description:
//  Verilog module sirv_gnrl DFF with Load-enable and Reset
//  Default reset value is 1
//
// ===========================================================================
module dfflrs # (
  parameter DW = 32
) (

  input               lden, 
  input      [DW-1:0] dnxt,
  output     [DW-1:0] qout,

  input               clk,
  input               rst_n
);

reg [DW-1:0] qout_r;

always @(posedge clk or negedge rst_n)
begin : DFFLRS_PROC
  if (rst_n == 1'b0)
    qout_r <= {DW{1'b1}};
  else if (lden == 1'b1)
    qout_r <= #1 dnxt;
end

assign qout = qout_r;


endmodule
// ===========================================================================
//
// Description:
//  Verilog module sirv_gnrl DFF with Load-enable and Reset
//  Default reset value is 0
//
// ===========================================================================

module dfflr # (
  parameter DW = 32
) (

  input               lden, 
  input      [DW-1:0] dnxt,
  output     [DW-1:0] qout,

  input               clk,
  input               rst_n
);

reg [DW-1:0] qout_r;

always @(posedge clk or negedge rst_n)
begin : DFFLR_PROC
  if (rst_n == 1'b0)
    qout_r <= {DW{1'b0}};
  else if (lden == 1'b1)
    qout_r <= #1 dnxt;
end

assign qout = qout_r;


endmodule
// ===========================================================================
//
// Description:
//  Verilog module sirv_gnrl DFF with Load-enable, no reset 
//
// ===========================================================================

module dffl # (
  parameter DW = 32
) (

  input               lden, 
  input      [DW-1:0] dnxt,
  output     [DW-1:0] qout,

  input               clk 
);

reg [DW-1:0] qout_r;

always @(posedge clk)
begin : DFFL_PROC
  if (lden == 1'b1)
    qout_r <= #1 dnxt;
end

assign qout = qout_r;


endmodule
// ===========================================================================
//
// Description:
//  Verilog module sirv_gnrl DFF with Reset, no load-enable
//  Default reset value is 1
//
// ===========================================================================

module dffrs # (
  parameter DW = 32
) (

  input      [DW-1:0] dnxt,
  output     [DW-1:0] qout,

  input               clk,
  input               rst_n
);

reg [DW-1:0] qout_r;

always @(posedge clk or negedge rst_n)
begin : DFFRS_PROC
  if (rst_n == 1'b0)
    qout_r <= {DW{1'b0}};
  else                  
    qout_r <= /*#1*/ dnxt;
end

assign qout = qout_r;

endmodule
// ===========================================================================
//
// Description:
//  Verilog module sirv_gnrl DFF with Reset, no load-enable
//  Default reset value is 0
//
// ===========================================================================

module dffr # (
  parameter DW = 32
) (

  input      [DW-1:0] dnxt,
  output     [DW-1:0] qout,

  input               clk,
  input               rst_n
);

reg [DW-1:0] qout_r;

always @(posedge clk or negedge rst_n)
begin : DFFR_PROC
  if (rst_n == 1'b0)
    qout_r <= {DW{1'b0}};
  else                  
    qout_r <= #1 dnxt;
end

assign qout = qout_r;

endmodule
// ===========================================================================
//
// Description:
//  Verilog module for general latch 
//
// ===========================================================================

module sirv_gnrl_ltch # (
  parameter DW = 32
) (

  //input               test_mode,
  input               lden, 
  input      [DW-1:0] dnxt,
  output     [DW-1:0] qout
);

reg [DW-1:0] qout_r;

always @ (*) 
begin : LTCH_PROC
  if (lden == 1'b1)
    qout_r <= dnxt;
end

//assign qout = test_mode ? dnxt : qout_r;
assign qout = qout_r;


endmodule

count_pulse.v
module count_pulse # (
  parameter DW = 8
) (
  output qout,
  input [DW-1:0] in,
  input lden,
  input clk,
  input rst_n
);

  wire [DW-1:0] cur_cnt;
  wire [DW-1:0] nxt_cnt;
  wire [DW-1:0] minus_one;
  wire pos;

  assign pos = (cur_cnt > 0);
  assign minus_one =
          ({DW{ pos}} & cur_cnt - 1)
        | ({DW{~pos}} & 0);

  assign nxt_cnt =
          ({DW{~lden}} & minus_one)
        | ({DW{ lden}} & in);

  assign qout = (cur_cnt > 0) & clk;

  dffr #(DW) cnt_dffr (nxt_cnt, cur_cnt, clk, rst_n);

endmodule

diffdev.v
module diffdev # (
  parameter DW = 8
) (
  output [DW-1:0] output_count,
  output [DW-1:0] change_price,
  input [DW-1:0] total_insert,
  input [DW-1:0] total_price,
  input [DW-1:0] input_count
);

  wire [DW-1:0] diff;
  wire enough;

  assign diff = total_insert - total_price;
  assign enough = diff[DW-1] == 1'b0;
  assign change_price =
          ({DW{ enough}} & diff)
        | ({DW{~enough}} & total_insert);
  assign output_count = {DW{enough}} & input_count;

endmodule

insert_cnt.v
module insert_counter # (
  parameter DW = 8
) (
  output [DW-1:0] qout,
    
  input clk,
  input rst_n
);

  wire [DW-1:0] cur_cnt;
  wire [DW-1:0] nxt_cnt;

  assign nxt_cnt =
          ({DW{ rst_n}} & cur_cnt + 1)
        | ({DW{~rst_n}} & {DW{1'b0}});

  assign qout = cur_cnt;

  dffr #(DW) cnt_dffr (nxt_cnt, cur_cnt, clk, rst_n);

endmodule

abs.v
module abs # (
  parameter DW = 8
) (
  output [DW-1:0] out,
  input [DW-1:0] in
);

  wire neg;

  assign neg = in[DW-1] == 1'b1;
  assign abs =
          ({DW{~neg}} &  in)
        | ({DW{ neg}} & -in);
  assign out = abs;

endmodule

dest_selector.v
module dest_selector # (
  parameter DW = 8,
  parameter MYID = 16
) (
  output [DW-1:0] total,
  output [DW-1:0] ticket,
  input [DW-1:0] dest,
  input [DW-1:0] count
);

  wire valid;
  wire [DW-1:0] diff;
  wire [DW-1:0] dist;
  wire [DW-1:0] price;

  assign valid = dest != MYID;
  assign diff = dest - MYID;
  assign price = (dist - 1) / 5 + 2;
  assign total = valid ? price * count : 0;
  assign ticket = valid ? count : 0;
  
  abs #(8) abs_dist (dist, diff);

endmodule

oneshot.v
module oneshot (
  output out,
  input in,
  input clk
);

  wire curr;
  wire prev;

  assign out = (curr == 1'b1) & (prev == 1'b0);

  assign curr = in;
  sirv_gnrl_ltch #(1) oneshot_dffrs (clk, curr, prev);

endmodule

vendor.v
module vendor # (
  parameter DW = 8,
  parameter MYID = 16
) (
  output ticket_pulse,
  output coin_one_out_pulse,

  input [DW-1:0] input_dest,
  input [DW-1:0] input_count,
  input coin_one_in_pulse,
  input coin_ten_in_pulse,
  input done,
  input clk,
  input rst_n
);

  wire [DW-1:0] checked_input_ticket_count;
  wire [DW-1:0] coin_one_cnt;
  wire [DW-1:0] coin_ten_cnt;
  wire [DW-1:0] total_insert;
  wire [DW-1:0] total_price;
  wire [DW-1:0] output_ticket_count;
  wire [DW-1:0] change_price;
  wire [DW-1:0] change_one_cnt;
  wire done_oneshot;

  oneshot done_shooter (done_oneshot, done, clk);

  dest_selector #(DW, MYID) dest_device (total_price,
                                          checked_input_ticket_count,
                                          input_dest,
                                          input_count);

  insert_counter #(DW) coin_one_counter (coin_one_cnt, coin_one_in_pulse, rst_n);
  insert_counter #(DW) coin_ten_counter (coin_ten_cnt, coin_ten_in_pulse, rst_n);

  assign total_insert = coin_one_cnt + coin_ten_cnt * 10;

  diffdev #(DW) diff_device (output_ticket_count,
                            change_price,
                            total_insert,
                            total_price,
                            checked_input_ticket_count);

  assign change_one_cnt = change_price;

  count_pulse #(DW) change_one_pulser (coin_one_out_pulse,
                                        change_one_cnt,
                                        done_oneshot,
                                        clk,
                                        rst_n);

  count_pulse #(DW) ticket_pulser (ticket_pulse,
                                    output_ticket_count,
                                    done_oneshot,
                                    clk,
                                    rst_n);

endmodule

tb.v
`timescale 1s/1ms
module tb;

wire ticket;
wire one_output;
wire ten_output;

reg [7:0] dest;
reg [7:0] count;
reg one_insert;
reg ten_insert;
reg done;

reg clk;
reg rst_n;

vendor #(8, 16) v0 (ticket,
                    one_output,
                    dest,
                    count,
                    one_insert,
                    ten_insert,
                    done,
                    clk,
                    rst_n);

initial begin
    $dumpfile("vendor.vcd");
    $dumpvars(0, tb);
end

always #(0.5)
    clk = ~clk;

initial begin
    // startup

    // reset input
    dest <= 16;
    count <= 0;
    one_insert <= 0;
    ten_insert <= 0;
    done <= 0;

    // reset clk and reset
    clk <= 1'b0;
    rst_n <= 1'b0;

    // turn of reset
    #(2)
    rst_n <= 1'b1;

    // work

    #(10)
    dest <= 15; // price 2/ticket
    count <= 3; // total 6
    #(1) one_insert <= 1;
    #(1) one_insert <= 0;
    #(1) one_insert <= 1;
    #(1) one_insert <= 0;
    #(1) ten_insert <= 1;
    #(1) ten_insert <= 0; // insert 12
    #(1) done <= 1;
    #(2) done <= 0;

    #(20) $finish;
end

endmodule

vendor.vcd
$date
	Thu Nov 17 22:19:28 2022
$end
$version
	Icarus Verilog
$end
$timescale
	1ms
$end
$scope module tb $end
$var wire 1 ! ticket $end
$var wire 1 " one_output $end
$var reg 1 # clk $end
$var reg 8 $ count [7:0] $end
$var reg 8 % dest [7:0] $end
$var reg 1 & done $end
$var reg 1 ' one_insert $end
$var reg 1 ( rst_n $end
$var reg 1 ) ten_insert $end
$scope module v0 $end
$var wire 8 * change_one_cnt [7:0] $end
$var wire 1 # clk $end
$var wire 1 ' coin_one_in_pulse $end
$var wire 1 ) coin_ten_in_pulse $end
$var wire 1 & done $end
$var wire 8 + input_count [7:0] $end
$var wire 8 , input_dest [7:0] $end
$var wire 1 ( rst_n $end
$var wire 8 - total_price [7:0] $end
$var wire 8 . total_insert [7:0] $end
$var wire 1 ! ticket_pulse $end
$var wire 8 / output_ticket_count [7:0] $end
$var wire 1 0 done_oneshot $end
$var wire 8 1 coin_ten_cnt [7:0] $end
$var wire 1 " coin_one_out_pulse $end
$var wire 8 2 coin_one_cnt [7:0] $end
$var wire 8 3 checked_input_ticket_count [7:0] $end
$var wire 8 4 change_price [7:0] $end
$scope module change_one_pulser $end
$var wire 1 # clk $end
$var wire 8 5 in [7:0] $end
$var wire 8 6 minus_one [7:0] $end
$var wire 8 7 nxt_cnt [7:0] $end
$var wire 1 " qout $end
$var wire 1 ( rst_n $end
$var wire 1 8 pos $end
$var wire 1 0 lden $end
$var wire 8 9 cur_cnt [7:0] $end
$scope module cnt_dffr $end
$var wire 1 # clk $end
$var wire 8 : dnxt [7:0] $end
$var wire 1 ( rst_n $end
$var wire 8 ; qout [7:0] $end
$var reg 8 < qout_r [7:0] $end
$scope begin DFFR_PROC $end
$upscope $end
$upscope $end
$upscope $end
$scope module coin_one_counter $end
$var wire 1 ' clk $end
$var wire 8 = nxt_cnt [7:0] $end
$var wire 8 > qout [7:0] $end
$var wire 1 ( rst_n $end
$var wire 8 ? cur_cnt [7:0] $end
$scope module cnt_dffr $end
$var wire 1 ' clk $end
$var wire 8 @ dnxt [7:0] $end
$var wire 1 ( rst_n $end
$var wire 8 A qout [7:0] $end
$var reg 8 B qout_r [7:0] $end
$scope begin DFFR_PROC $end
$upscope $end
$upscope $end
$upscope $end
$scope module coin_ten_counter $end
$var wire 1 ) clk $end
$var wire 8 C nxt_cnt [7:0] $end
$var wire 8 D qout [7:0] $end
$var wire 1 ( rst_n $end
$var wire 8 E cur_cnt [7:0] $end
$scope module cnt_dffr $end
$var wire 1 ) clk $end
$var wire 8 F dnxt [7:0] $end
$var wire 1 ( rst_n $end
$var wire 8 G qout [7:0] $end
$var reg 8 H qout_r [7:0] $end
$scope begin DFFR_PROC $end
$upscope $end
$upscope $end
$upscope $end
$scope module dest_device $end
$var wire 8 I count [7:0] $end
$var wire 8 J dest [7:0] $end
$var wire 1 K valid $end
$var wire 8 L total [7:0] $end
$var wire 8 M ticket [7:0] $end
$var wire 8 N price [7:0] $end
$var wire 8 O dist [7:0] $end
$var wire 8 P diff [7:0] $end
$scope module abs_dist $end
$var wire 8 Q abs [7:0] $end
$var wire 8 R in [7:0] $end
$var wire 1 S neg $end
$var wire 8 T out [7:0] $end
$upscope $end
$upscope $end
$scope module diff_device $end
$var wire 8 U change_price [7:0] $end
$var wire 1 V enough $end
$var wire 8 W input_count [7:0] $end
$var wire 8 X output_count [7:0] $end
$var wire 8 Y total_insert [7:0] $end
$var wire 8 Z total_price [7:0] $end
$var wire 8 [ diff [7:0] $end
$upscope $end
$scope module done_shooter $end
$var wire 1 # clk $end
$var wire 1 \ curr $end
$var wire 1 & in $end
$var wire 1 0 out $end
$var wire 1 ] prev $end
$scope module oneshot_dffrs $end
$var wire 1 \ dnxt $end
$var wire 1 # lden $end
$var wire 1 ] qout $end
$var reg 1 ] qout_r $end
$scope begin LTCH_PROC $end
$upscope $end
$upscope $end
$upscope $end
$scope module ticket_pulser $end
$var wire 1 # clk $end
$var wire 8 ^ in [7:0] $end
$var wire 1 0 lden $end
$var wire 8 _ minus_one [7:0] $end
$var wire 8 ` nxt_cnt [7:0] $end
$var wire 1 ! qout $end
$var wire 1 ( rst_n $end
$var wire 1 a pos $end
$var wire 8 b cur_cnt [7:0] $end
$scope module cnt_dffr $end
$var wire 1 # clk $end
$var wire 8 c dnxt [7:0] $end
$var wire 1 ( rst_n $end
$var wire 8 d qout [7:0] $end
$var reg 8 e qout_r [7:0] $end
$scope begin DFFR_PROC $end
$upscope $end
$upscope $end
$upscope $end
$upscope $end
$upscope $end
$enddefinitions $end
#0
$dumpvars
b0 e
b0 d
b0 c
b0 b
0a
b0 `
b0 _
b0 ^
x]
0\
b0 [
b0 Z
b0 Y
b0 X
b0 W
1V
b0 U
b0 T
0S
b0 R
b0 Q
b0 P
b0 O
b110101 N
b0 M
b0 L
0K
b10000 J
b0 I
b0 H
b0 G
b0 F
b0 E
b0 D
b0 C
b0 B
b0 A
b0 @
b0 ?
b0 >
b0 =
b0 <
b0 ;
b0 :
b0 9
08
b0 7
b0 6
b0 5
b0 4
b0 3
b0 2
b0 1
00
b0 /
b0 .
b0 -
b10000 ,
b0 +
b0 *
0)
0(
0'
0&
b10000 %
b0 $
0#
0"
0!
$end
#500
0]
1#
#1000
0#
#1500
1#
#2000
b1 =
b1 @
b1 C
b1 F
1(
0#
#2500
1#
#3000
0#
#3500
1#
#4000
0#
#4500
1#
#5000
0#
#5500
1#
#6000
0#
#6500
1#
#7000
0#
#7500
1#
#8000
0#
#8500
1#
#9000
0#
#9500
1#
#10000
0#
#10500
1#
#11000
0#
#11500
1#
#12000
0V
b10 N
b0 *
b0 5
b0 4
b0 U
b1 O
b1 T
b1 Q
1S
b0 /
b0 X
b0 ^
b11111010 [
b110 -
b110 L
b110 Z
b11 3
b11 M
b11 W
b11111111 P
b11111111 R
b11 $
b11 +
b11 I
1K
b1111 %
b1111 ,
b1111 J
0#
#12500
1#
#13000
b10 =
b10 @
b1 *
b1 5
b1 4
b1 U
b11111011 [
b1 .
b1 Y
b1 2
b1 >
b1 ?
b1 A
b1 B
1'
0#
#13500
1#
#14000
0'
0#
#14500
1#
#15000
b11 =
b11 @
b10 *
b10 5
b10 4
b10 U
b11111100 [
b10 .
b10 Y
b10 2
b10 >
b10 ?
b10 A
b10 B
1'
0#
#15500
1#
#16000
0'
0#
#16500
1#
#17000
b11 /
b11 X
b11 ^
b10 C
b10 F
b110 *
b110 5
b110 4
b110 U
1V
b110 [
b1100 .
b1100 Y
b1 1
b1 D
b1 E
b1 G
b1 H
1)
0#
#17500
1#
#18000
0)
0#
#18500
1#
#19000
b11 `
b11 c
b110 7
b110 :
10
1\
1&
0#
#19500
b10 `
b10 c
b101 7
b101 :
b10 _
b101 6
00
1!
1"
1a
b11 b
b11 d
b11 e
18
b110 9
b110 ;
b110 <
1]
1#
#20000
0"
0!
0#
#20500
b1 `
b1 c
b100 7
b100 :
b1 _
b100 6
b10 b
b10 d
b10 e
b101 9
b101 ;
b101 <
1"
1!
1#
#21000
0\
0&
0"
0!
0#
#21500
b0 `
b0 c
b11 7
b11 :
b0 _
b11 6
b1 b
b1 d
b1 e
b100 9
b100 ;
b100 <
0]
1"
1!
1#
#22000
0"
0!
0#
#22500
b10 7
b10 :
b10 6
0a
b0 b
b0 d
b0 e
b11 9
b11 ;
b11 <
1"
0!
1#
#23000
0"
0#
#23500
b1 7
b1 :
b1 6
b10 9
b10 ;
b10 <
1"
1#
#24000
0"
0#
#24500
b0 7
b0 :
b0 6
b1 9
b1 ;
b1 <
1"
1#
#25000
0"
0#
#25500
08
b0 9
b0 ;
b0 <
0"
1#
