dff.v
// ===========================================================================
//
// Description:
//  Verilog module sirv_gnrl DFF with Load-enable and Reset
//  Default reset value is 1
//
// ===========================================================================
module dfflrs # (
  parameter DW = 32
) (

  input               lden, 
  input      [DW-1:0] dnxt,
  output     [DW-1:0] qout,

  input               clk,
  input               rst_n
);

reg [DW-1:0] qout_r;

always @(posedge clk or negedge rst_n)
begin : DFFLRS_PROC
  if (rst_n == 1'b0)
    qout_r <= {DW{1'b1}};
  else if (lden == 1'b1)
    qout_r <= #1 dnxt;
end

assign qout = qout_r;


endmodule
// ===========================================================================
//
// Description:
//  Verilog module sirv_gnrl DFF with Load-enable and Reset
//  Default reset value is 0
//
// ===========================================================================

module dfflr # (
  parameter DW = 32
) (

  input               lden, 
  input      [DW-1:0] dnxt,
  output     [DW-1:0] qout,

  input               clk,
  input               rst_n
);

reg [DW-1:0] qout_r;

always @(posedge clk or negedge rst_n)
begin : DFFLR_PROC
  if (rst_n == 1'b0)
    qout_r <= {DW{1'b0}};
  else if (lden == 1'b1)
    qout_r <= #1 dnxt;
end

assign qout = qout_r;


endmodule
// ===========================================================================
//
// Description:
//  Verilog module sirv_gnrl DFF with Load-enable, no reset 
//
// ===========================================================================

module dffl # (
  parameter DW = 32
) (

  input               lden, 
  input      [DW-1:0] dnxt,
  output     [DW-1:0] qout,

  input               clk 
);

reg [DW-1:0] qout_r;

always @(posedge clk)
begin : DFFL_PROC
  if (lden == 1'b1)
    qout_r <= #1 dnxt;
end

assign qout = qout_r;


endmodule
// ===========================================================================
//
// Description:
//  Verilog module sirv_gnrl DFF with Reset, no load-enable
//  Default reset value is 1
//
// ===========================================================================

module dffrs # (
  parameter DW = 32
) (

  input      [DW-1:0] dnxt,
  output     [DW-1:0] qout,

  input               clk,
  input               rst_n
);

reg [DW-1:0] qout_r;

always @(posedge clk or negedge rst_n)
begin : DFFRS_PROC
  if (rst_n == 1'b0)
    qout_r <= {DW{1'b0}};
  else                  
    qout_r <= /*#1*/ dnxt;
end

assign qout = qout_r;

endmodule
// ===========================================================================
//
// Description:
//  Verilog module sirv_gnrl DFF with Reset, no load-enable
//  Default reset value is 0
//
// ===========================================================================

module dffr # (
  parameter DW = 32
) (

  input      [DW-1:0] dnxt,
  output     [DW-1:0] qout,

  input               clk,
  input               rst_n
);

reg [DW-1:0] qout_r;

always @(posedge clk or negedge rst_n)
begin : DFFR_PROC
  if (rst_n == 1'b0)
    qout_r <= {DW{1'b0}};
  else                  
    qout_r <= #1 dnxt;
end

assign qout = qout_r;

endmodule
// ===========================================================================
//
// Description:
//  Verilog module for general latch 
//
// ===========================================================================

module sirv_gnrl_ltch # (
  parameter DW = 32
) (

  //input               test_mode,
  input               lden, 
  input      [DW-1:0] dnxt,
  output     [DW-1:0] qout
);

reg [DW-1:0] qout_r;

always @ (*) 
begin : LTCH_PROC
  if (lden == 1'b1)
    qout_r <= dnxt;
end

//assign qout = test_mode ? dnxt : qout_r;
assign qout = qout_r;


endmodule

count_pulse.v
module count_pulse # (
  parameter DW = 8
) (
  output qout,
  input [DW-1:0] in,
  input lden,
  input clk,
  input rst_n
);

  wire [DW-1:0] cur_cnt;
  wire [DW-1:0] nxt_cnt;
  wire [DW-1:0] minus_one;
  wire pos;

  assign pos = (cur_cnt > 0);
  assign minus_one =
          ({DW{ pos}} & cur_cnt - 1)
        | ({DW{~pos}} & 0);

  assign nxt_cnt =
          ({DW{~lden}} & minus_one)
        | ({DW{ lden}} & in);

  assign qout = (cur_cnt > 0) & clk;

  dffr #(DW) cnt_dffr (nxt_cnt, cur_cnt, clk, rst_n);

endmodule

diffdev.v
module diffdev # (
  parameter DW = 8
) (
  output [DW-1:0] output_count,
  output [DW-1:0] change_price,
  input [DW-1:0] total_insert,
  input [DW-1:0] total_price,
  input [DW-1:0] input_count
);

  wire [DW-1:0] diff;
  wire enough;

  assign diff = total_insert - total_price;
  assign enough = diff[DW-1] == 1'b0;
  assign change_price =
          ({DW{ enough}} & diff)
        | ({DW{~enough}} & total_insert);
  assign output_count = {DW{enough}} & input_count;

endmodule

insert_cnt.v
module insert_counter # (
  parameter DW = 8
) (
  output [DW-1:0] qout,
    
  input clk,
  input rst_n
);

  wire [DW-1:0] cur_cnt;
  wire [DW-1:0] nxt_cnt;

  assign nxt_cnt =
          ({DW{ rst_n}} & cur_cnt + 1)
        | ({DW{~rst_n}} & {DW{1'b0}});

  assign qout = cur_cnt;

  dffr #(DW) cnt_dffr (nxt_cnt, cur_cnt, clk, rst_n);

endmodule

abs.v
module abs # (
  parameter DW = 8
) (
  output [DW-1:0] out,
  input [DW-1:0] in
);

  wire neg;

  assign neg = in[DW-1] == 1'b1;
  assign abs =
          ({DW{~neg}} &  in)
        | ({DW{ neg}} & -in);
  assign out = abs;

endmodule

dest_selector.v
module dest_selector # (
  parameter DW = 8
) (
  output [DW-1:0] total,
  output [DW-1:0] ticket,
  input [DW-1:0] src,
  input [DW-1:0] dest,
  input [DW-1:0] count
);

  wire valid;
  wire [DW-1:0] diff;
  wire [DW-1:0] dist;
  wire [DW-1:0] price;
  wire [1:0] dir_src;
  wire [1:0] dir_dest;
  wire [DW-3:0] val_src;
  wire [DW-3:0] val_dest;
  wire switch;
  wire [DW-1:0] checked_count;

  assign valid = dest != src;
  assign dir_src = src >> (DW-2);
  assign dir_dest = dest >> (DW-2);
  assign val_src = src & {(DW-2){1'b1}};
  assign val_dest = dest & {(DW-2){1'b1}};
  assign switch = dir_src != dir_dest;

  assign diff = switch ? (val_dest + val_src) : (val_dest - val_src);

  assign checked_count = (count > 4) ? 4 : count;
  assign price = (dist - 1) / 5 + 2;
  assign total = valid ? price * checked_count : 0;
  assign ticket = valid ? checked_count : 0;
  
  abs #(8) abs_dist (dist, diff);

endmodule

oneshot.v
module oneshot (
  output out,
  input in,
  input clk
);

  wire curr;
  wire prev;

  assign out = (curr == 1'b1) & (prev == 1'b0);

  assign curr = in;
  sirv_gnrl_ltch #(1) oneshot_dffrs (clk, curr, prev);

endmodule

vendor.v
module vendor # (
  parameter DW = 8
) (
  output ticket_pulse,
  output coin_one_out_pulse,

  input [DW-1:0] input_src,
  input [DW-1:0] input_dest,
  input [DW-1:0] input_count,
  input coin_ten_in_pulse,
  input done,
  input clk,
  input rst_n
);

  wire [DW-1:0] checked_input_ticket_count;
  wire [DW-1:0] coin_ten_cnt;
  wire [DW-1:0] total_insert;
  wire [DW-1:0] total_price;
  wire [DW-1:0] output_ticket_count;
  wire [DW-1:0] change_price;
  wire [DW-1:0] change_one_cnt;
  wire done_oneshot;

  oneshot done_shooter (done_oneshot, done, clk);

  dest_selector #(DW) dest_device (total_price,
                                    checked_input_ticket_count,
                                    input_src,
                                    input_dest,
                                    input_count);

  insert_counter #(DW) coin_ten_counter (coin_ten_cnt, coin_ten_in_pulse, rst_n & ~delayed_done_oneshot);

  dffr #(DW) done_lagger (
    .dnxt(done_oneshot),
    .qout(delayed_done_oneshot),
    .clk(clk),
    .rst_n(rst_n)
  );

  assign total_insert = coin_ten_cnt * 10;

  diffdev #(DW) diff_device (output_ticket_count,
                            change_price,
                            total_insert,
                            total_price,
                            checked_input_ticket_count);

  assign change_one_cnt = change_price;

  count_pulse #(DW) change_one_pulser (coin_one_out_pulse,
                                        change_one_cnt,
                                        done_oneshot,
                                        clk,
                                        rst_n);

  count_pulse #(DW) ticket_pulser (ticket_pulse,
                                    output_ticket_count,
                                    done_oneshot,
                                    clk,
                                    rst_n);

endmodule

tb.v
`timescale 1s/1ms
module tb;

wire ticket;
wire one_output;
wire ten_output;

reg [7:0] src;
reg [7:0] dest;
reg [7:0] count;
reg ten_insert;
reg done;

reg clk;
reg rst_n;

vendor #(8, 16) v0 (ticket,
                    one_output,
                    src,
                    dest,
                    count,
                    ten_insert,
                    done,
                    clk,
                    rst_n);

initial begin
    $dumpfile("vendor.vcd");
    $dumpvars(0, tb);
end

always #(0.5)
    clk = ~clk;

initial begin
    // startup

    // reset input
    src <= 0;
    dest <= 0;
    count <= 0;
    ten_insert <= 0;
    done <= 0;

    // reset clk and reset
    clk <= 1'b0;
    rst_n <= 1'b0;

    // turn of reset
    #(2)
    rst_n <= 1'b1;

    // work

    #(10)
    src <=  8'b10000111;
    dest <= 8'b10000001; // price 3/ticket
    count <= 3; // total 9
    #(1) ten_insert <= 1;
    #(1) ten_insert <= 0; // insert 10, change 1
    #(1) done <= 1;
    #(2) done <= 0;

    #(10)
    src <=  8'b10000010;
    dest <= 8'b11010001; // price 5/ticket
    count <= 5; // total 20
    #(1) ten_insert <= 1;
    #(1) ten_insert <= 0;
    #(1) ten_insert <= 1;
    #(1) ten_insert <= 0; // insert 20, change 0
    #(1) done <= 1;
    #(2) done <= 0;

    #(10)
    src <=  8'b00000101;
    dest <= 8'b10001011; // price 5/ticket
    count <= 3; // total 15
    #(1) ten_insert <= 1;
    #(1) ten_insert <= 0;
    #(1) ten_insert <= 1;
    #(1) ten_insert <= 0; // insert 20, change 5
    #(1) done <= 1;
    #(2) done <= 0;

    #(10)
    src <=  8'b00000101;
    dest <= 8'b10001011; // price 5/ticket
    count <= 3; // total 15
    #(1) ten_insert <= 1;
    #(1) ten_insert <= 0; // insert 10, no ticket
    #(1) done <= 1;
    #(2) done <= 0;

    #(20) $finish;
end

endmodule

vendor.vcd
$date
	Mon Apr 10 09:05:09 2023
$end
$version
	Icarus Verilog
$end
$timescale
	1ms
$end
$scope module tb $end
$var wire 1 ! ticket $end
$var wire 1 " one_output $end
$var reg 1 # clk $end
$var reg 8 $ count [7:0] $end
$var reg 8 % dest [7:0] $end
$var reg 1 & done $end
$var reg 1 ' rst_n $end
$var reg 8 ( src [7:0] $end
$var reg 1 ) ten_insert $end
$scope module v0 $end
$var wire 8 * change_one_cnt [7:0] $end
$var wire 1 # clk $end
$var wire 1 ) coin_ten_in_pulse $end
$var wire 1 & done $end
$var wire 8 + input_count [7:0] $end
$var wire 8 , input_dest [7:0] $end
$var wire 8 - input_src [7:0] $end
$var wire 1 ' rst_n $end
$var wire 8 . total_price [7:0] $end
$var wire 8 / total_insert [7:0] $end
$var wire 1 ! ticket_pulse $end
$var wire 8 0 output_ticket_count [7:0] $end
$var wire 1 1 done_oneshot $end
$var wire 1 2 delayed_done_oneshot $end
$var wire 8 3 coin_ten_cnt [7:0] $end
$var wire 1 " coin_one_out_pulse $end
$var wire 8 4 checked_input_ticket_count [7:0] $end
$var wire 8 5 change_price [7:0] $end
$scope module change_one_pulser $end
$var wire 1 # clk $end
$var wire 8 6 in [7:0] $end
$var wire 8 7 minus_one [7:0] $end
$var wire 8 8 nxt_cnt [7:0] $end
$var wire 1 " qout $end
$var wire 1 ' rst_n $end
$var wire 1 9 pos $end
$var wire 1 1 lden $end
$var wire 8 : cur_cnt [7:0] $end
$scope module cnt_dffr $end
$var wire 1 # clk $end
$var wire 8 ; dnxt [7:0] $end
$var wire 1 ' rst_n $end
$var wire 8 < qout [7:0] $end
$var reg 8 = qout_r [7:0] $end
$scope begin DFFR_PROC $end
$upscope $end
$upscope $end
$upscope $end
$scope module coin_ten_counter $end
$var wire 1 ) clk $end
$var wire 8 > nxt_cnt [7:0] $end
$var wire 8 ? qout [7:0] $end
$var wire 1 @ rst_n $end
$var wire 8 A cur_cnt [7:0] $end
$scope module cnt_dffr $end
$var wire 1 ) clk $end
$var wire 8 B dnxt [7:0] $end
$var wire 1 @ rst_n $end
$var wire 8 C qout [7:0] $end
$var reg 8 D qout_r [7:0] $end
$scope begin DFFR_PROC $end
$upscope $end
$upscope $end
$upscope $end
$scope module dest_device $end
$var wire 8 E count [7:0] $end
$var wire 8 F dest [7:0] $end
$var wire 8 G src [7:0] $end
$var wire 1 H valid $end
$var wire 6 I val_src [5:0] $end
$var wire 6 J val_dest [5:0] $end
$var wire 8 K total [7:0] $end
$var wire 8 L ticket [7:0] $end
$var wire 1 M switch $end
$var wire 8 N price [7:0] $end
$var wire 8 O dist [7:0] $end
$var wire 2 P dir_src [1:0] $end
$var wire 2 Q dir_dest [1:0] $end
$var wire 8 R diff [7:0] $end
$var wire 8 S checked_count [7:0] $end
$scope module abs_dist $end
$var wire 8 T abs [7:0] $end
$var wire 8 U in [7:0] $end
$var wire 1 V neg $end
$var wire 8 W out [7:0] $end
$upscope $end
$upscope $end
$scope module diff_device $end
$var wire 8 X change_price [7:0] $end
$var wire 1 Y enough $end
$var wire 8 Z input_count [7:0] $end
$var wire 8 [ output_count [7:0] $end
$var wire 8 \ total_insert [7:0] $end
$var wire 8 ] total_price [7:0] $end
$var wire 8 ^ diff [7:0] $end
$upscope $end
$scope module done_lagger $end
$var wire 1 # clk $end
$var wire 8 _ dnxt [7:0] $end
$var wire 1 ' rst_n $end
$var wire 8 ` qout [7:0] $end
$var reg 8 a qout_r [7:0] $end
$scope begin DFFR_PROC $end
$upscope $end
$upscope $end
$scope module done_shooter $end
$var wire 1 # clk $end
$var wire 1 b curr $end
$var wire 1 & in $end
$var wire 1 1 out $end
$var wire 1 c prev $end
$scope module oneshot_dffrs $end
$var wire 1 b dnxt $end
$var wire 1 # lden $end
$var wire 1 c qout $end
$var reg 1 c qout_r $end
$scope begin LTCH_PROC $end
$upscope $end
$upscope $end
$upscope $end
$scope module ticket_pulser $end
$var wire 1 # clk $end
$var wire 8 d in [7:0] $end
$var wire 1 1 lden $end
$var wire 8 e minus_one [7:0] $end
$var wire 8 f nxt_cnt [7:0] $end
$var wire 1 ! qout $end
$var wire 1 ' rst_n $end
$var wire 1 g pos $end
$var wire 8 h cur_cnt [7:0] $end
$scope module cnt_dffr $end
$var wire 1 # clk $end
$var wire 8 i dnxt [7:0] $end
$var wire 1 ' rst_n $end
$var wire 8 j qout [7:0] $end
$var reg 8 k qout_r [7:0] $end
$scope begin DFFR_PROC $end
$upscope $end
$upscope $end
$upscope $end
$upscope $end
$upscope $end
$enddefinitions $end
#0
$dumpvars
b0 k
b0 j
b0 i
b0 h
0g
b0 f
b0 e
b0 d
xc
0b
b0 a
b0 `
b0 _
b0 ^
b0 ]
b0 \
b0 [
b0 Z
1Y
b0 X
b0 W
0V
b0 U
b0 T
b0 S
b0 R
b0 Q
b0 P
b0 O
b110101 N
0M
b0 L
b0 K
b0 J
b0 I
0H
b0 G
b0 F
b0 E
b0 D
b0 C
b0 B
b0 A
0@
b0 ?
b0 >
b0 =
b0 <
b0 ;
b0 :
09
b0 8
b0 7
b0 6
b0 5
b0 4
b0 3
02
01
b0 0
b0 /
b0 .
b0 -
b0 ,
b0 +
b0 *
0)
b0 (
0'
0&
b0 %
b0 $
0#
0"
0!
$end
#500
0c
1#
#1000
0#
#1500
1#
#2000
b1 >
b1 B
1@
1'
0#
#2500
1#
#3000
0#
#3500
1#
#4000
0#
#4500
1#
#5000
0#
#5500
1#
#6000
0#
#6500
1#
#7000
0#
#7500
1#
#8000
0#
#8500
1#
#9000
0#
#9500
1#
#10000
0#
#10500
1#
#11000
0#
#11500
1#
#12000
0Y
b11 N
b110 O
b110 W
b110 T
1V
b0 *
b0 6
b0 5
b0 X
b0 0
b0 [
b0 d
b11111010 R
b11111010 U
b11110111 ^
b1001 .
b1001 K
b1001 ]
b11 4
b11 L
b11 Z
b1 J
b10 Q
b111 I
0M
b10 P
b11 S
b11 $
b11 +
b11 E
b10000001 %
b10000001 ,
b10000001 F
1H
b10000111 (
b10000111 -
b10000111 G
0#
#12500
1#
#13000
b11 0
b11 [
b11 d
b10 >
b10 B
b1 *
b1 6
b1 5
b1 X
1Y
b1 ^
b1010 /
b1010 \
b1 3
b1 ?
b1 A
b1 C
b1 D
1)
0#
#13500
1#
#14000
0)
0#
#14500
1#
#15000
b11 f
b11 i
b1 8
b1 ;
b1 _
11
1b
1&
0#
#15500
b0 0
b0 [
b0 d
0Y
b0 *
b0 6
b0 5
b0 X
b11110111 ^
b0 /
b0 \
b0 3
b0 ?
b0 A
b0 C
b0 D
b0 >
b0 B
b10 f
b10 i
b0 8
b0 ;
0@
b10 e
b0 _
01
1!
1"
12
1g
b11 h
b11 j
b11 k
19
b1 :
b1 <
b1 =
b1 `
b1 a
1c
1#
#16000
0"
0!
0#
#16500
b1 >
b1 B
b1 f
b1 i
1@
b1 e
02
b10 h
b10 j
b10 k
09
b0 :
b0 <
b0 =
b0 `
b0 a
0"
1!
1#
#17000
0b
0&
0!
0#
#17500
b0 f
b0 i
b0 e
b1 h
b1 j
b1 k
0c
1!
1#
#18000
0!
0#
#18500
0g
b0 h
b0 j
b0 k
0!
1#
#19000
0#
#19500
1#
#20000
0#
#20500
1#
#21000
0#
#21500
1#
#22000
0#
#22500
1#
#23000
0#
#23500
1#
#24000
0#
#24500
1#
#25000
0#
#25500
1#
#26000
0#
#26500
1#
#27000
b0 *
b0 6
b0 5
b0 X
b0 0
b0 [
b0 d
0Y
b101 N
0V
b10011 O
b10011 W
b10011 T
b10011 R
b10011 U
b11101100 ^
b10100 .
b10100 K
b10100 ]
b100 4
b100 L
b100 Z
b10001 J
1M
b11 Q
b10 I
b100 S
b101 $
b101 +
b101 E
b11010001 %
b11010001 ,
b11010001 F
b10000010 (
b10000010 -
b10000010 G
0#
#27500
1#
#28000
b10 >
b10 B
b1010 *
b1010 6
b1010 5
b1010 X
b11110110 ^
b1010 /
b1010 \
b1 3
b1 ?
b1 A
b1 C
b1 D
1)
0#
#28500
1#
#29000
0)
0#
#29500
1#
#30000
b100 0
b100 [
b100 d
b11 >
b11 B
b0 *
b0 6
b0 5
b0 X
1Y
b0 ^
b10100 /
b10100 \
b10 3
b10 ?
b10 A
b10 C
b10 D
1)
0#
#30500
1#
#31000
0)
0#
#31500
1#
#32000
b100 f
b100 i
b1 _
11
1b
1&
0#
#32500
b0 0
b0 [
b0 d
0Y
b0 *
b0 6
b0 5
b0 X
b11101100 ^
b0 /
b0 \
b0 3
b0 ?
b0 A
b0 C
b0 D
b0 >
b0 B
b11 f
b11 i
0@
b11 e
b0 _
01
1!
12
1g
b100 h
b100 j
b100 k
b1 `
b1 a
1c
1#
#33000
0!
0#
#33500
b1 >
b1 B
b10 f
b10 i
1@
b10 e
02
b11 h
b11 j
b11 k
b0 `
b0 a
1!
1#
#34000
0b
0&
0!
0#
#34500
b1 f
b1 i
b1 e
b10 h
b10 j
b10 k
0c
1!
1#
#35000
0!
0#
#35500
b0 f
b0 i
b0 e
b1 h
b1 j
b1 k
1!
1#
#36000
0!
0#
#36500
0g
b0 h
b0 j
b0 k
0!
1#
#37000
0#
#37500
1#
#38000
0#
#38500
1#
#39000
0#
#39500
1#
#40000
0#
#40500
1#
#41000
0#
#41500
1#
#42000
0#
#42500
1#
#43000
0#
#43500
1#
#44000
b10000 O
b10000 W
b10000 T
b10000 R
b10000 U
b11110001 ^
b1111 .
b1111 K
b1111 ]
b11 4
b11 L
b11 Z
b1011 J
b10 Q
b101 I
b0 P
b11 S
b11 $
b11 +
b11 E
b10001011 %
b10001011 ,
b10001011 F
b101 (
b101 -
b101 G
0#
#44500
1#
#45000
b10 >
b10 B
b1010 *
b1010 6
b1010 5
b1010 X
b11111011 ^
b1010 /
b1010 \
b1 3
b1 ?
b1 A
b1 C
b1 D
1)
0#
#45500
1#
#46000
0)
0#
#46500
1#
#47000
b11 0
b11 [
b11 d
b11 >
b11 B
b101 *
b101 6
b101 5
b101 X
1Y
b101 ^
b10100 /
b10100 \
b10 3
b10 ?
b10 A
b10 C
b10 D
1)
0#
#47500
1#
#48000
0)
0#
#48500
1#
#49000
b11 f
b11 i
b101 8
b101 ;
b1 _
11
1b
1&
0#
#49500
b0 0
b0 [
b0 d
0Y
b0 *
b0 6
b0 5
b0 X
b11110001 ^
b0 /
b0 \
b0 3
b0 ?
b0 A
b0 C
b0 D
b0 >
b0 B
b10 f
b10 i
b100 8
b100 ;
0@
b10 e
b100 7
b0 _
01
1!
1"
12
1g
b11 h
b11 j
b11 k
19
b101 :
b101 <
b101 =
b1 `
b1 a
1c
1#
#50000
0"
0!
0#
#50500
b1 >
b1 B
b1 f
b1 i
b11 8
b11 ;
1@
b1 e
b11 7
02
b10 h
b10 j
b10 k
b100 :
b100 <
b100 =
b0 `
b0 a
1"
1!
1#
#51000
0b
0&
0"
0!
0#
#51500
b0 f
b0 i
b10 8
b10 ;
b0 e
b10 7
b1 h
b1 j
b1 k
b11 :
b11 <
b11 =
0c
1"
1!
1#
#52000
0"
0!
0#
#52500
b1 8
b1 ;
b1 7
0g
b0 h
b0 j
b0 k
b10 :
b10 <
b10 =
1"
0!
1#
#53000
0"
0#
#53500
b0 8
b0 ;
b0 7
b1 :
b1 <
b1 =
1"
1#
#54000
0"
0#
#54500
09
b0 :
b0 <
b0 =
0"
1#
#55000
0#
#55500
1#
#56000
0#
#56500
1#
#57000
0#
#57500
1#
#58000
0#
#58500
1#
#59000
0#
#59500
1#
#60000
0#
#60500
1#
#61000
0#
#61500
1#
#62000
b10 >
b10 B
b1010 *
b1010 6
b1010 5
b1010 X
b11111011 ^
b1010 /
b1010 \
b1 3
b1 ?
b1 A
b1 C
b1 D
1)
0#
#62500
1#
#63000
0)
0#
#63500
1#
#64000
b1010 8
b1010 ;
b1 _
11
1b
1&
0#
#64500
b0 *
b0 6
b0 5
b0 X
b11110001 ^
b0 /
b0 \
b0 3
b0 ?
b0 A
b0 C
b0 D
b0 >
b0 B
b1001 8
b1001 ;
0@
b1001 7
b0 _
01
1"
12
19
b1010 :
b1010 <
b1010 =
b1 `
b1 a
1c
1#
#65000
0"
0#
#65500
b1 >
b1 B
b1000 8
b1000 ;
1@
b1000 7
02
b1001 :
b1001 <
b1001 =
b0 `
b0 a
1"
1#
#66000
0b
0&
0"
0#
#66500
b111 8
b111 ;
b111 7
b1000 :
b1000 <
b1000 =
0c
1"
1#
#67000
0"
0#
#67500
b110 8
b110 ;
b110 7
b111 :
b111 <
b111 =
1"
1#
#68000
0"
0#
#68500
b101 8
b101 ;
b101 7
b110 :
b110 <
b110 =
1"
1#
#69000
0"
0#
#69500
b100 8
b100 ;
b100 7
b101 :
b101 <
b101 =
1"
1#
#70000
0"
0#
#70500
b11 8
b11 ;
b11 7
b100 :
b100 <
b100 =
1"
1#
#71000
0"
0#
#71500
b10 8
b10 ;
b10 7
b11 :
b11 <
b11 =
1"
1#
#72000
0"
0#
#72500
b1 8
b1 ;
b1 7
b10 :
b10 <
b10 =
1"
1#
#73000
0"
0#
#73500
b0 8
b0 ;
b0 7
b1 :
b1 <
b1 =
1"
1#
#74000
0"
0#
#74500
09
b0 :
b0 <
b0 =
0"
1#
